e2xgrader_core/__init__.py
e2xgrader_core/_version.py
e2xgrader_core/api.py
e2xgrader_core/utils.py
e2xgrader_core/apps/__init__.py
e2xgrader_core/apps/api.py
e2xgrader_core/apps/course_info.py
e2xgrader_core/apps/shared_materials.py
e2xgrader_core/base/__init__.py
e2xgrader_core/base/app.py
e2xgrader_core/base/extension.py
e2xgrader_core/base/grader.py
e2xgrader_core/base/handlers.py
e2xgrader_core/cells/e2xgrader.py
e2xgrader_core/cells/nbgrader.py
e2xgrader_core/config/__init__.py
e2xgrader_core/config/base_config.py
e2xgrader_core/exporters/__init__.py
e2xgrader_core/exporters/exporter.py
e2xgrader_core/exporters/filters/__init__.py
e2xgrader_core/exporters/filters/highlightlinenumbers.py
e2xgrader_core/exporters/templates/e2xgrader/conf.json
e2xgrader_core/exporters/templates/e2xgrader/index.html.j2
e2xgrader_core/preprocessors/__init__.py
e2xgrader_core/preprocessors/preprocess_cell.py
e2xgrader_core/server_extension/__init__.py
e2xgrader_core/server_extension/core.py
e2xgrader_core/tests/__init__.py
e2xgrader_core/tests/test_handlers.py
e2xgrader_core-0.1.0a1.data/data/etc/jupyter/jupyter_server_config.d/e2xgrader_core.json
e2xgrader_core-0.1.0a1.data/data/share/jupyter/nbconvert/templates/e2xgrader/conf.json
e2xgrader_core-0.1.0a1.data/data/share/jupyter/nbconvert/templates/e2xgrader/index.html.j2
e2xgrader_core-0.1.0a1.data/data/share/jupyter/labextensions/@e2xgrader/core/package.json
e2xgrader_core-0.1.0a1.data/data/share/jupyter/labextensions/@e2xgrader/core/schemas/@e2xgrader/core/cell-factory.json
e2xgrader_core-0.1.0a1.data/data/share/jupyter/labextensions/@e2xgrader/core/schemas/@e2xgrader/core/package.json.orig
e2xgrader_core-0.1.0a1.data/data/share/jupyter/labextensions/@e2xgrader/core/static/181.f1db1cbfceb9d3b36433.js
e2xgrader_core-0.1.0a1.data/data/share/jupyter/labextensions/@e2xgrader/core/static/800.bc39ad5e6baddf7afbde.js
e2xgrader_core-0.1.0a1.data/data/share/jupyter/labextensions/@e2xgrader/core/static/remoteEntry.a3bd3231ac291a564185.js
e2xgrader_core-0.1.0a1.dist-info/METADATA
e2xgrader_core-0.1.0a1.dist-info/WHEEL
e2xgrader_core-0.1.0a1.dist-info/entry_points.txt
e2xgrader_core-0.1.0a1.dist-info/licenses/LICENSE
e2xgrader_core-0.1.0a1.dist-info/RECORD
