Metadata-Version: 2.4
Name: e2xgrader_core
Version: 0.1.0a1
Summary: A JupyterLab extension providing core functionality for e2xgrader
Project-URL: Homepage, https://github.com/e2xgrader/e2xgrader-core
Project-URL: Bug Tracker, https://github.com/e2xgrader/e2xgrader-core/issues
Project-URL: Repository, https://github.com/e2xgrader/e2xgrader-core.git
Author-email: Tim Metzler <tim.metzler@h-brs.de>
License: BSD 3-Clause License
License-File: LICENSE
Keywords: jupyter,jupyterlab,jupyterlab-extension
Classifier: Framework :: Jupyter
Classifier: Framework :: Jupyter :: JupyterLab
Classifier: Framework :: Jupyter :: JupyterLab :: 4
Classifier: Framework :: Jupyter :: JupyterLab :: Extensions
Classifier: Framework :: Jupyter :: JupyterLab :: Extensions :: Prebuilt
Classifier: License :: OSI Approved :: BSD License
Classifier: Programming Language :: Python
Classifier: Programming Language :: Python :: 3
Classifier: Programming Language :: Python :: 3.9
Classifier: Programming Language :: Python :: 3.10
Classifier: Programming Language :: Python :: 3.11
Classifier: Programming Language :: Python :: 3.12
Classifier: Programming Language :: Python :: 3.13
Requires-Python: >=3.9
Requires-Dist: jupyter-server<3,>=2.4.0
Requires-Dist: nbgrader>=0.9.0
Provides-Extra: docs
Requires-Dist: pydata-sphinx-theme; extra == 'docs'
Requires-Dist: sphinx; extra == 'docs'
Provides-Extra: test
Requires-Dist: coverage; extra == 'test'
Requires-Dist: pytest; extra == 'test'
Requires-Dist: pytest-asyncio; extra == 'test'
Requires-Dist: pytest-cov; extra == 'test'
Requires-Dist: pytest-jupyter[server]>=0.6.0; extra == 'test'
